odoo/addons/fieldservice_project/README.rst
odoo/addons/fieldservice_project/__init__.py
odoo/addons/fieldservice_project/__manifest__.py
odoo/addons/fieldservice_project/i18n/de.po
odoo/addons/fieldservice_project/i18n/es.po
odoo/addons/fieldservice_project/i18n/es_CL.po
odoo/addons/fieldservice_project/i18n/fieldservice_project.pot
odoo/addons/fieldservice_project/i18n/pt_BR.po
odoo/addons/fieldservice_project/models/__init__.py
odoo/addons/fieldservice_project/models/fsm_location.py
odoo/addons/fieldservice_project/models/fsm_order.py
odoo/addons/fieldservice_project/models/fsm_team.py
odoo/addons/fieldservice_project/models/project.py
odoo/addons/fieldservice_project/models/project_task.py
odoo/addons/fieldservice_project/readme/CONTRIBUTORS.rst
odoo/addons/fieldservice_project/readme/CREDITS.rst
odoo/addons/fieldservice_project/readme/DESCRIPTION.rst
odoo/addons/fieldservice_project/readme/ROADMAP.rst
odoo/addons/fieldservice_project/readme/USAGE.rst
odoo/addons/fieldservice_project/security/ir.model.access.csv
odoo/addons/fieldservice_project/static/description/icon.png
odoo/addons/fieldservice_project/static/description/index.html
odoo/addons/fieldservice_project/static/src/scss/project_column.scss
odoo/addons/fieldservice_project/views/fsm_location_views.xml
odoo/addons/fieldservice_project/views/fsm_order_views.xml
odoo/addons/fieldservice_project/views/fsm_team.xml
odoo/addons/fieldservice_project/views/project_task_views.xml
odoo/addons/fieldservice_project/views/project_views.xml
odoo12_addon_fieldservice_project-12.0.1.2.1.dist-info/METADATA
odoo12_addon_fieldservice_project-12.0.1.2.1.dist-info/WHEEL
odoo12_addon_fieldservice_project-12.0.1.2.1.dist-info/top_level.txt
odoo12_addon_fieldservice_project-12.0.1.2.1.dist-info/RECORD
