Metadata-Version: 2.1
Name: odoo12-addon-fieldservice-project
Version: 12.0.1.2.1
Summary: Create field service orders from a project or project task
Home-page: https://github.com/OCA/field-service
Author: Pavlov Media, Odoo Community Association (OCA)
Author-email: support@odoo-community.org
License: AGPL-3
Platform: UNKNOWN
Classifier: Programming Language :: Python
Classifier: Framework :: Odoo
Classifier: License :: OSI Approved :: GNU Affero General Public License v3
Requires-Python: >=3.5
Requires-Dist: odoo12-addon-fieldservice
Requires-Dist: odoo (<12.1dev,>=12.0a)
